pytexture/__init__.py
pytexture-0.1.dist-info/METADATA
pytexture-0.1.dist-info/RECORD
pytexture-0.1.dist-info/WHEEL
pytexture-0.1.dist-info/top_level.txt
