Metadata-Version: 2.1
Name: pytexture
Version: 0.1
Summary: Generates image textures for digital art
Home-page: https://github.com/martinmcbride/pytexture
Author: Martin McBride
Author-email: mcbride.martin@gmail.com
License: MIT
Platform: UNKNOWN
Classifier: Programming Language :: Python :: 3
Classifier: License :: OSI Approved :: MIT License
Classifier: Operating System :: OS Independent
